boltons/__init__.py
boltons/cacheutils.py
boltons/debugutils.py
boltons/deprutils.py
boltons/dictutils.py
boltons/easterutils.py
boltons/ecoutils.py
boltons/excutils.py
boltons/fileutils.py
boltons/formatutils.py
boltons/funcutils.py
boltons/gcutils.py
boltons/ioutils.py
boltons/iterutils.py
boltons/jsonutils.py
boltons/listutils.py
boltons/mathutils.py
boltons/mboxutils.py
boltons/namedutils.py
boltons/pathutils.py
boltons/queueutils.py
boltons/setutils.py
boltons/socketutils.py
boltons/statsutils.py
boltons/strutils.py
boltons/tableutils.py
boltons/tbutils.py
boltons/timeutils.py
boltons/typeutils.py
boltons/urlutils.py
boltons-23.1.0.dist-info/LICENSE
boltons-23.1.0.dist-info/METADATA
boltons-23.1.0.dist-info/WHEEL
boltons-23.1.0.dist-info/top_level.txt
boltons-23.1.0.dist-info/RECORD
